qfmu/__init__.py
qfmu/__main__.py
qfmu/cli.py
qfmu/utils.py
qfmu/codegen/__init__.py
qfmu/codegen/utils.py
qfmu/codegen/include/fmi2FunctionTypes.h
qfmu/codegen/include/fmi2Functions.h
qfmu/codegen/include/fmi2Template.c
qfmu/codegen/include/fmi2Template.h
qfmu/codegen/include/fmi2TypesPlatform.h
qfmu/codegen/templates/fmi2model.jinja
qfmu/codegen/templates/fmi2modelDescription.jinja
qfmu/model/__init__.py
qfmu/model/lti.py
qfmu/model/pid.py
qfmu/model/ss.py
qfmu/model/tf.py
qfmu/model/zpk.py
qfmu-0.2.9.dist-info/LICENSE
qfmu-0.2.9.dist-info/METADATA
qfmu-0.2.9.dist-info/WHEEL
qfmu-0.2.9.dist-info/entry_points.txt
qfmu-0.2.9.dist-info/top_level.txt
qfmu-0.2.9.dist-info/RECORD
