Metadata-Version: 2.1
Name: qfmu
Version: 0.2.9
Summary: Quickly generate an FMU from command line
Home-page: https://github.com/hyumo/qfmu
Author: Hang Yu
Author-email: yuhang.neu@gmail.com
License: BSD license
Keywords: qfmu
Classifier: Natural Language :: English
Classifier: Intended Audience :: Developers
Classifier: License :: OSI Approved :: BSD License
Classifier: Programming Language :: Python :: 3 :: Only
Classifier: Programming Language :: Python :: 3.8
Classifier: Programming Language :: Python :: 3.9
Classifier: Programming Language :: Python :: 3.10
Classifier: Programming Language :: Python :: 3.11
Classifier: Topic :: Software Development :: Libraries
Requires-Python: >=3.8
License-File: LICENSE
Requires-Dist: annotated-types ==0.6.0
Requires-Dist: Jinja2 ==3.1.2
Requires-Dist: numpy ==1.24.4
Requires-Dist: scipy ==1.10.1
Requires-Dist: click ==8.1.7
Requires-Dist: typing-extensions ==4.8.0
Provides-Extra: dev
Requires-Dist: wheel ; extra == 'dev'
Requires-Dist: pip ; extra == 'dev'
Requires-Dist: setuptools ; extra == 'dev'
Requires-Dist: pytest ; extra == 'dev'
Requires-Dist: ruff ; extra == 'dev'
Requires-Dist: coverage ; extra == 'dev'
Requires-Dist: pytest-cov ; extra == 'dev'
Requires-Dist: black ; extra == 'dev'
Requires-Dist: isort ; extra == 'dev'
Requires-Dist: twine ; extra == 'dev'
Requires-Dist: build ; extra == 'dev'
Requires-Dist: bump2version ; extra == 'dev'
Requires-Dist: mypy ; extra == 'dev'
Requires-Dist: pipreqs ; extra == 'dev'
Requires-Dist: pandas ; extra == 'dev'
Requires-Dist: fmpy ==0.3.16 ; extra == 'dev'
